streamlit_carbon_button/__init__.py
streamlit_carbon_button/carbon_icons.py
streamlit_carbon_button/frontend/index.html
streamlit_carbon_button/frontend/static/css/main.DLlhL_l-.css
streamlit_carbon_button/frontend/static/js/main.DSD8LoQW.js
streamlit_carbon_button/frontend/static/js/main.DSD8LoQW.js.map
streamlit_carbon_button-1.4.0.dist-info/licenses/LICENSE
streamlit_carbon_button-1.4.0.dist-info/licenses/NOTICE
streamlit_carbon_button-1.4.0.dist-info/METADATA
streamlit_carbon_button-1.4.0.dist-info/WHEEL
streamlit_carbon_button-1.4.0.dist-info/top_level.txt
streamlit_carbon_button-1.4.0.dist-info/RECORD
