Metadata-Version: 2.4
Name: streamlit-carbon-button
Version: 1.4.0
Summary: Carbon Design System buttons for Streamlit
Home-page: https://github.com/yourusername/streamlit-carbon-button-dev
Author: Your Name
Author-email: Your Name <your.email@example.com>
Maintainer-email: Your Name <your.email@example.com>
License-Expression: MIT
Project-URL: Homepage, https://github.com/yourusername/streamlit-carbon-button-dev
Project-URL: Documentation, https://github.com/yourusername/streamlit-carbon-button-examples
Project-URL: Repository, https://github.com/yourusername/streamlit-carbon-button-dev
Project-URL: Issues, https://github.com/yourusername/streamlit-carbon-button-dev/issues
Project-URL: Examples, https://github.com/yourusername/streamlit-carbon-button-examples
Keywords: streamlit,carbon,design-system,buttons,ui,components
Classifier: Development Status :: 5 - Production/Stable
Classifier: Intended Audience :: Developers
Classifier: Programming Language :: Python :: 3
Classifier: Programming Language :: Python :: 3.8
Classifier: Programming Language :: Python :: 3.9
Classifier: Programming Language :: Python :: 3.10
Classifier: Programming Language :: Python :: 3.11
Classifier: Programming Language :: Python :: 3.12
Classifier: Topic :: Software Development :: Libraries :: Python Modules
Classifier: Topic :: Software Development :: User Interfaces
Requires-Python: >=3.8
License-File: LICENSE
License-File: NOTICE
Requires-Dist: streamlit>=1.0.0
Provides-Extra: dev
Requires-Dist: pytest>=7.4.0; extra == "dev"
Requires-Dist: pytest-cov>=4.1.0; extra == "dev"
Requires-Dist: black>=24.0.0; extra == "dev"
Requires-Dist: ruff>=0.3.0; extra == "dev"
Requires-Dist: pre-commit>=3.5.0; extra == "dev"
Dynamic: author
Dynamic: home-page
Dynamic: license-file
Dynamic: requires-python
